README.md
setup.py
flitton_fib_py/__init__.py
flitton_fib_py/cmd/__init__.py
flitton_fib_py/cmd/fib_numb.py
flitton_fib_py/fib_calcs/__init__.py
flitton_fib_py/fib_calcs/fib_number.py
flitton_fib_py/fib_calcs/fib_numbers.py
flitton_fib_py1.egg-info/PKG-INFO
flitton_fib_py1.egg-info/SOURCES.txt
flitton_fib_py1.egg-info/dependency_links.txt
flitton_fib_py1.egg-info/entry_points.txt
flitton_fib_py1.egg-info/top_level.txt
tests/flitton_fib_py/__init__.py
tests/flitton_fib_py/fib_calcs/__init__.py
tests/flitton_fib_py/fib_calcs/test_fib_number.py
tests/flitton_fib_py/fib_calcs/test_fib_numbers.py